stain/__init__.py
stain/api.py
stain-0.1.dist-info/METADATA
stain-0.1.dist-info/RECORD
stain-0.1.dist-info/WHEEL
stain-0.1.dist-info/top_level.txt
