Metadata-Version: 2.1
Name: stain
Version: 0.1
Summary: Taking care of the dirty parts of terminal colors.
Home-page: https://github.com/erinish/stain
Author: Eric Rinish
Author-email: erinish@users.noreply.github.com
License: MIT
Platform: UNKNOWN
Classifier: License :: OSI Approved :: MIT License
Classifier: Programming Language :: Python
Classifier: Programming Language :: Python :: 3
Classifier: Programming Language :: Python :: 3.4
Classifier: Programming Language :: Python :: 3.5
Classifier: Programming Language :: Python :: 3.6
Classifier: Programming Language :: Python :: 3.7
Requires-Python: >=3.4.0
